fileflows/__init__.py
fileflows/core.py
fileflows/s3.py
fileflows/utils.py
fileflows-0.2.8.dist-info/METADATA
fileflows-0.2.8.dist-info/WHEEL
fileflows-0.2.8.dist-info/top_level.txt
fileflows-0.2.8.dist-info/RECORD
