Metadata-Version: 2.2
Name: fileflows
Version: 0.2.8
Summary: A single high-level file operations API for both object stores and local file system.
Author-email: Dan Kelleher <kelleherjdan@gmail.com>
License: MIT
Classifier: Programming Language :: Python
Classifier: Programming Language :: Python :: 3
Classifier: Topic :: Software Development
Classifier: Topic :: Software Development :: Libraries
Classifier: Topic :: Software Development :: Libraries :: Python Modules
Requires-Dist: tqdm
Requires-Dist: s3fs[boto3]
Requires-Dist: pydantic>=2.0.0
Requires-Dist: pydantic-settings
Requires-Dist: quicklogs>=2.0.0
Requires-Dist: pyarrow
Requires-Dist: duckdb
Requires-Dist: xxhash
Provides-Extra: dev
Requires-Dist: black; extra == "dev"
Requires-Dist: pytest; extra == "dev"
